README.rst
setup.cfg
setup.py
tgext/__init__.py
tgext.scss.egg-info/PKG-INFO
tgext.scss.egg-info/SOURCES.txt
tgext.scss.egg-info/dependency_links.txt
tgext.scss.egg-info/entry_points.txt
tgext.scss.egg-info/namespace_packages.txt
tgext.scss.egg-info/not-zip-safe
tgext.scss.egg-info/requires.txt
tgext.scss.egg-info/top_level.txt
tgext/scss/__init__.py
tgext/scss/middleware.py