Metadata-Version: 1.1
Name: tgext.scss
Version: 0.4.2
Summary: SCSS for TurboGears2, fast middleware to use SCSS for all your CSS
Home-page: http://bitbucket.org/_amol_/tgext.scss
Author: Alessandro Molina
Author-email: alessandro.molina@axant.it
License: MIT
Keywords: turbogears2.extension SCSS WSGI
Platform: UNKNOWN
Classifier: Environment :: Web Environment
Classifier: Topic :: Software Development :: Libraries :: Python Modules
Classifier: Framework :: TurboGears
